asv_bench_memray/__init__.py
asv_bench_memray/benchmarks/__init__.py
asv_bench_memray/benchmarks/raymem.py
asv_bench_memray-0.1.2.dist-info/METADATA
asv_bench_memray-0.1.2.dist-info/WHEEL
asv_bench_memray-0.1.2.dist-info/licenses/LICENSE
asv_bench_memray-0.1.2.dist-info/RECORD
