Metadata-Version: 2.1
Name: asv_bench_memray
Version: 0.1.2
Summary: A memray benchmark plugin for asv
Project-URL: Documentation, https://haozeke.github.io/asv_bench_memray/
Project-URL: Issues, https://github.com/HaoZeke/asv_bench_memray/issues
Project-URL: Source, https://github.com/HaoZeke/asv_bench_memray
Author-email: Rohit Goswami <rgoswami@ieee.org>
Maintainer-email: Rohit Goswami <rgoswami@ieee.org>
License: MIT
License-File: LICENSE
Requires-Python: >=3.8
Requires-Dist: asv-runner>=0.2.0
Requires-Dist: memray>=1.7.0
Provides-Extra: lint
Requires-Dist: ruff>=0.0.265; extra == 'lint'
Provides-Extra: rel
Requires-Dist: tbump; extra == 'rel'
Requires-Dist: towncrier; extra == 'rel'
